basalam_sdk/__init__.py
basalam_sdk/auth.py
basalam_sdk/basalam_client.py
basalam_sdk/basalam_client.pyi
basalam_sdk/base_client.py
basalam_sdk/config.py
basalam_sdk/errors.py
basalam_sdk/py.typed
basalam_sdk/version.py
basalam_sdk/chat/__init__.py
basalam_sdk/chat/client.py
basalam_sdk/chat/models.py
basalam_sdk/core/__init__.py
basalam_sdk/core/client.py
basalam_sdk/core/models.py
basalam_sdk/order/__init__.py
basalam_sdk/order/client.py
basalam_sdk/order/models.py
basalam_sdk/order_processing/__init__.py
basalam_sdk/order_processing/client.py
basalam_sdk/order_processing/models.py
basalam_sdk/search/__init__.py
basalam_sdk/search/client.py
basalam_sdk/search/models.py
basalam_sdk/upload/__init__.py
basalam_sdk/upload/client.py
basalam_sdk/upload/models.py
basalam_sdk/wallet/__init__.py
basalam_sdk/wallet/client.py
basalam_sdk/wallet/models.py
basalam_sdk/webhook/__init__.py
basalam_sdk/webhook/client.py
basalam_sdk/webhook/models.py
basalam_sdk-1.1.5.dist-info/METADATA
basalam_sdk-1.1.5.dist-info/WHEEL
basalam_sdk-1.1.5.dist-info/licenses/LICENSE
basalam_sdk-1.1.5.dist-info/RECORD
