Metadata-Version: 2.4
Name: basalam-sdk
Version: 1.1.5
Summary: A comprehensive Python client library for interacting with Basalam API services
Project-URL: Homepage, https://github.com/basalam/python-sdk
Project-URL: Repository, https://github.com/basalam/python-sdk.git
Project-URL: Issues, https://github.com/basalam/python-sdk/issues
Author-email: Basalam Development Team <developers@basalam.com>
License-Expression: MIT
License-File: LICENSE
Keywords: api,async,basalam,client,e-commerce,sdk
Classifier: Development Status :: 4 - Beta
Classifier: Intended Audience :: Developers
Classifier: License :: OSI Approved :: MIT License
Classifier: Operating System :: OS Independent
Classifier: Programming Language :: Python :: 3
Classifier: Programming Language :: Python :: 3 :: Only
Classifier: Programming Language :: Python :: 3.9
Classifier: Programming Language :: Python :: 3.10
Classifier: Programming Language :: Python :: 3.11
Classifier: Programming Language :: Python :: 3.12
Classifier: Topic :: Software Development :: Libraries :: Python Modules
Classifier: Typing :: Typed
Requires-Python: >=3.9
Requires-Dist: httpx>=0.24.0
Requires-Dist: pydantic<3.0.0,>=2.0.0
Requires-Dist: python-dateutil>=2.8.2
Provides-Extra: dev
Requires-Dist: black>=23.7.0; extra == 'dev'
Requires-Dist: isort>=5.12.0; extra == 'dev'
Requires-Dist: mypy>=1.5.0; extra == 'dev'
Requires-Dist: pytest-asyncio>=0.21.0; extra == 'dev'
Requires-Dist: pytest-cov>=4.1.0; extra == 'dev'
Requires-Dist: pytest>=7.4.0; extra == 'dev'
Requires-Dist: ruff>=0.0.290; extra == 'dev'
Provides-Extra: lint
Requires-Dist: black>=23.7.0; extra == 'lint'
Requires-Dist: isort>=5.12.0; extra == 'lint'
Requires-Dist: mypy>=1.5.0; extra == 'lint'
Requires-Dist: ruff>=0.0.290; extra == 'lint'
Provides-Extra: test
Requires-Dist: pytest-asyncio>=0.21.0; extra == 'test'
Requires-Dist: pytest-cov>=4.1.0; extra == 'test'
Requires-Dist: pytest-mock>=3.11.1; extra == 'test'
Requires-Dist: pytest>=7.4.0; extra == 'test'
Requires-Dist: respx>=0.20.0; extra == 'test'
